internetarchive/__init__.py
internetarchive/__version__.py
internetarchive/account.py
internetarchive/api.py
internetarchive/auth.py
internetarchive/catalog.py
internetarchive/config.py
internetarchive/exceptions.py
internetarchive/files.py
internetarchive/iarequest.py
internetarchive/item.py
internetarchive/py.typed
internetarchive/search.py
internetarchive/session.py
internetarchive/utils.py
internetarchive/cli/__init__.py
internetarchive/cli/cli_utils.py
internetarchive/cli/ia.py
internetarchive/cli/ia_account.py
internetarchive/cli/ia_configure.py
internetarchive/cli/ia_copy.py
internetarchive/cli/ia_delete.py
internetarchive/cli/ia_download.py
internetarchive/cli/ia_flag.py
internetarchive/cli/ia_list.py
internetarchive/cli/ia_metadata.py
internetarchive/cli/ia_move.py
internetarchive/cli/ia_reviews.py
internetarchive/cli/ia_search.py
internetarchive/cli/ia_simplelists.py
internetarchive/cli/ia_tasks.py
internetarchive/cli/ia_upload.py
internetarchive/cli/py.typed
internetarchive-5.7.2.dist-info/licenses/LICENSE
internetarchive-5.7.2.dist-info/METADATA
internetarchive-5.7.2.dist-info/WHEEL
internetarchive-5.7.2.dist-info/entry_points.txt
internetarchive-5.7.2.dist-info/top_level.txt
internetarchive-5.7.2.dist-info/RECORD
