Metadata-Version: 2.4
Name: internetarchive
Version: 5.7.2
Summary: A Python interface to archive.org.
Home-page: https://github.com/jjjake/internetarchive
Author: Jacob M. Johnson
Author-email: jake@archive.org
License: AGPL-3.0
Classifier: Development Status :: 5 - Production/Stable
Classifier: Intended Audience :: Developers
Classifier: License :: OSI Approved :: GNU Affero General Public License v3
Classifier: Natural Language :: English
Classifier: Programming Language :: Python
Classifier: Programming Language :: Python :: 3
Classifier: Programming Language :: Python :: 3 :: Only
Classifier: Programming Language :: Python :: Implementation :: CPython
Classifier: Programming Language :: Python :: Implementation :: PyPy
Requires-Python: >=3.9
License-File: LICENSE
Requires-Dist: jsonpatch>=0.4
Requires-Dist: requests<3.0.0,>=2.25.0
Requires-Dist: tqdm>=4.0.0
Requires-Dist: urllib3>=1.26.0
Requires-Dist: importlib-metadata>=3.6.0; python_version <= "3.10"
Provides-Extra: all
Requires-Dist: black; extra == "all"
Requires-Dist: mypy; extra == "all"
Requires-Dist: pre-commit; extra == "all"
Requires-Dist: pytest; extra == "all"
Requires-Dist: safety; extra == "all"
Requires-Dist: setuptools; extra == "all"
Requires-Dist: pytest==8.4.2; extra == "all"
Requires-Dist: responses==0.20.0; extra == "all"
Requires-Dist: ruff==0.14.1; extra == "all"
Requires-Dist: tqdm-stubs>=0.2.0; extra == "all"
Requires-Dist: types-colorama; extra == "all"
Requires-Dist: types-jsonpatch>=0.1.0a0; extra == "all"
Requires-Dist: types-pygments; extra == "all"
Requires-Dist: types-requests<3.0.0,>=2.25.0; extra == "all"
Requires-Dist: types-setuptools; extra == "all"
Requires-Dist: types-ujson>=4.2.0; extra == "all"
Requires-Dist: types-urllib3>=1.26.0; extra == "all"
Provides-Extra: dev
Requires-Dist: black; extra == "dev"
Requires-Dist: mypy; extra == "dev"
Requires-Dist: pre-commit; extra == "dev"
Requires-Dist: pytest; extra == "dev"
Requires-Dist: safety; extra == "dev"
Requires-Dist: setuptools; extra == "dev"
Provides-Extra: docs
Requires-Dist: alabaster==0.7.12; extra == "docs"
Requires-Dist: docutils<0.18; extra == "docs"
Requires-Dist: sphinx==4.5.0; extra == "docs"
Requires-Dist: sphinx-autodoc-typehints==1.18.1; extra == "docs"
Provides-Extra: test
Requires-Dist: pytest==8.4.2; extra == "test"
Requires-Dist: responses==0.20.0; extra == "test"
Requires-Dist: ruff==0.14.1; extra == "test"
Provides-Extra: types
Requires-Dist: tqdm-stubs>=0.2.0; extra == "types"
Requires-Dist: types-colorama; extra == "types"
Requires-Dist: types-jsonpatch>=0.1.0a0; extra == "types"
Requires-Dist: types-pygments; extra == "types"
Requires-Dist: types-requests<3.0.0,>=2.25.0; extra == "types"
Requires-Dist: types-setuptools; extra == "types"
Requires-Dist: types-ujson>=4.2.0; extra == "types"
Requires-Dist: types-urllib3>=1.26.0; extra == "types"
Dynamic: license-file
